[
  {
    "nombre": "Jovito Rodríguez",
    "imagen": "flores-izquierda1.png"
  },
  {
    "nombre": "Rosa Alba Rodríguez",
    "imagen": "flores-izquierda2.png"
  },
  {
    "nombre": "Rosaura Rodríguez",
    "imagen": "flores-izquierda3.png"
  },
  {
    "nombre": "Camila Rodríguez",
    "imagen": "flores-izquierda4.png"
  },
  {
    "nombre": "Valeria Rodríguez",
    "imagen": "flores-izquierda5.png"
  },
  {
    "nombre": "Jakeline Rodríguez",
    "imagen": "flores-izquierda6.png"
  },
  {
    "nombre": "Diego Rojas",
    "imagen": "flores-izquierda7.png"
  },
  {
    "nombre": "Vicente Rojas",
    "imagen": "flores-izquierda8.png"
  },
  {
    "nombre": "Marisol Rodríguez",
    "imagen": "flores-izquierda9.png"
  },
  {
    "nombre": "Stepanie Rodríguez",
    "imagen": "flores-izquierda10.png"
  },
  {
    "nombre": "David Alvaro",
    "imagen": "flores-izquierda11.png"
  },
  {
    "nombre": "Manuel Moraga Moreno",
    "imagen": "flores-izquierda12.png"
  },
  {
    "nombre": "Ligia Salazar",
    "imagen": "flores-izquierda13.png"
  },
  {
    "nombre": "Seily Moraga",
    "imagen": "flores-izquierda14.png"
  },
  {
    "nombre": "Maureen Moraga",
    "imagen": "flores-izquierda15.png"
  },
  {
    "nombre": "Ana Julia Moraga",
    "imagen": "flores-izquierda16.png"
  },
  {
    "nombre": "Miguel Porras",
    "imagen": "flores-izquierda17.png"
  },
  {
    "nombre": "Daniel Barrantes",
    "imagen": "flores-izquierda18.png"
  },
  {
    "nombre": "Daniel Murillo",
    "imagen": "flores-izquierda19.png"
  },
  {
    "nombre": "Marlon Villalobos",
    "imagen": "flores-izquierda20.png"
  },
  {
    "nombre": "Andrés Marin",
    "imagen": "flores-izquierda21.png"
  },
  {
    "nombre": "Marco Boniche",
    "imagen": "flores-izquierda22.png"
  },
  {
    "nombre": "Jeffrey Torres",
    "imagen": "flores-izquierda23.png"
  },
  {
    "nombre": "Gustavo Torres",
    "imagen": "flores-izquierda24.png"
  },
  {
    "nombre": "Marie Barquero",
    "imagen": "flores-izquierda25.png"
  },
  {
    "nombre": "Viviana Chevez",
    "imagen": "flores-izquierda26.png"
  },
  {
    "nombre": "Bryan Zuñiga",
    "imagen": "flores-izquierda27.png"
  },
  {
    "nombre": "José Salas",
    "imagen": "flores-izquierda28.png"
  },
  {
    "nombre": "Marlon Dailey",
    "imagen": "flores-izquierda29.png"
  },
  {
    "nombre": "Alonso Vega",
    "imagen": "flores-izquierda30.png"
  },
  {
    "nombre": "Jessica Madrigal",
    "imagen": "flores-izquierda31.png"
  }
]
